[
  {
    "title": "Кем была написана самая известная картина постимпрессионизма «Звездная ночь»?",
    "src": "https://s2.best-wallpaper.net/wallpaper/1920x1200/1111/Vincent-van-Gogh-Starry-Night_1920x1200.jpg",
    "correctAnswer": "1",
    "answers": [
      {
        "title": "Ван Гог",
        "value": "1"
      },
      {
        "title": "Айвазовский",
        "value": "2"
      },
      {
        "title": "Пикассо",
        "value": "3"
      },
      {
        "title": "Поль Гоген",
        "value": "4"
      }
    ]
  },
  
  {
    "title": "Кто написал «Тайную вечерю» за трехлетний период с 1495 по 1498?",
    "src": "https://img5.goodfon.ru/wallpaper/nbig/1/99/tainaia-vecheria-tainaia-vecheria-leonardo-da-vinchi-freska.jpg",
    "correctAnswer": "3",
    "answers": [
      {
        "title": "Микеланджело",
        "value": "1"
      },
      {
        "title": "Рафаэль",
        "value": "2"
      },
      {
        "title": "Леонардо да Винчи",
        "value": "3"
      },
      {
        "title": "Боттичелли",
        "value": "4"
      }
    ]
  },

  {
    "title": "Сколько лет Виктор Васнецов работал над своей знаменитой картиной «Богатыри»?",
    "src": "https://upload.wikimedia.org/wikipedia/commons/d/d3/Viktor_Vasnetsov_-_%D0%91%D0%BE%D0%B3%D0%B0%D1%82%D1%8B%D1%80%D0%B8_-_Google_Art_Project.jpg",
    "correctAnswer": "4",
    "answers": [
      {
        "title": "Около 5 лет",
        "value": "1"
      },
      {
        "title": "Около 10 лет",
        "value": "2"
      },
      {
        "title": "Около 15 лет",
        "value": "3"
      },
      {
        "title": "Около 20 лет",
        "value": "4"
      }
    ]
  },

  {
    "title": "Кто написал известное антивоенное произведение «Герника»?",
    "src": "https://e0.pxfuel.com/wallpapers/449/173/desktop-wallpaper-guernica-picasso.jpg",
    "correctAnswer": "1",
    "answers": [
      {
        "title": "Пикассо",
        "value": "1"
      },
      {
        "title": "Ван Гог",
        "value": "2"
      },
      {
        "title": "Сальвадор Дали",
        "value": "3"
      },
      {
        "title": "Клод Моне",
        "value": "4"
      }
    ]
  },

  {
    "title": "Какой художник написал «Крик», самую дорогую картину, когда-либо проданную на аукционе?",
    "src": "https://cdn.gallerix.asia/sr/M/1809742601/944233120.jpg",
    "correctAnswer": "2",
    "answers": [
      {
        "title": "Рембрандт",
        "value": "1"
      },
      {
        "title": "Эдвард Мунк",
        "value": "2"
      },
      {
        "title": "Энди Уорхол",
        "value": "3"
      },
      {
        "title": "Джорджия О'Кифф",
        "value": "4"
      }
    ]
  },

  {
    "title": "Как называется знаменитая скульптура человека Микеланджело?",
    "src": "https://planetofhotels.com/guide/sites/default/files/styles/paragraph__hero_banner__hb_image__1880bp/public/hero_banner/skulptura-davida.jpg",
    "correctAnswer": "3",
    "answers": [
      {
        "title": "Джозеф",
        "value": "1"
      },
      {
        "title": "Уильям",
        "value": "2"
      },
      {
        "title": "Давид",
        "value": "3"
      },
      {
        "title": "Питер",
        "value": "4"
      }
    ]
  },

  {
    "title": "В каком году Леонардо да Винчи написал «Мону Лизу»?",
    "src": "https://uploads0.wikiart.org/00339/images/leonardo-da-vinci/mona-lisa-c-1503-1519.jpg!Large.jpg",
    "correctAnswer": "2",
    "answers": [
      {
        "title": "1403",
        "value": "1"
      },
      {
        "title": "1503",
        "value": "2"
      },
      {
        "title": "1703",
        "value": "3"
      },
      {
        "title": "1603",
        "value": "4"
      }
    ]
  },

  {
    "title": "Свою знаменитую картину «Девятый вал» Айвазовский написал в 1850 году. В каком музее она хранится?",
    "src": "https://img3.goodfon.ru/wallpaper/nbig/e/78/ayvazovskiy-devyatyy-val-more.jpg",
    "correctAnswer": "1",
    "answers": [
      {
        "title": "Русский музей в Санкт-Петербурге",
        "value": "1"
      },
      {
        "title": "Эрмитаж в Санкт-Петербурге",
        "value": "2"
      },
      {
        "title": "Третьяковская галерея",
        "value": "3"
      },
      {
        "title": "Музей имени А.С. Пушкина",
        "value": "4"
      }
    ]
  },

  {
    "title": "Как называется эта известная картина Сандро Боттичелли?",
    "src": "https://img3.goodfon.ru/wallpaper/nbig/3/37/sandro-bottichelli-rozhdenie-venery-kartina-mifologiia.jpg",
    "correctAnswer": "3",
    "answers": [
      {
        "title": "Донна Велата",
        "value": "1"
      },
      {
        "title": "Даная",
        "value": "2"
      },
      {
        "title": "Рождение Венеры",
        "value": "3"
      },
      {
        "title": "Диана и Каллисто",
        "value": "4"
      }
    ]
  },

  {
    "title": "Кто помог пейзажисту Шишкину нарисовать медведей на его работе «Утро в сосновом бору»?",
    "src": "https://img3.goodfon.ru/wallpaper/nbig/d/c4/ivan-ivanovich-shishkin-les.jpg",
    "correctAnswer": "4",
    "answers": [
      {
        "title": "Репин",
        "value": "1"
      },
      {
        "title": "Чехов",
        "value": "2"
      },
      {
        "title": "Айвазовский",
        "value": "3"
      },
      {
        "title": "Савицкий",
        "value": "4"
      }
    ]
  }
]
